{
    "input_image_check": "https://files.catbox.moe/frdc2j.jpg",
    "positive_prompt": "detailed, realistic, masterpiece, uhd, 8k",
    "negative_prompt": "blurry",
    "inspire_seed": 9,
    "inspire_steps": 4,
    "inspire_cfg": 1.0,
    "inspire_sampler_name": "dpmpp_sde",
    "inspire_scheduler": "karras",
    "inspire_denoise": 0.6,
    "inspire_noise_mode": "GPU(=A1111)",
    "inspire_batch_seed_mode": "incremental",
    "inspire_variation_seed": 0,
    "inspire_variation_strength": 0.0,
    "inspire_variation_method": "linear",
    "scale_factor": 4.0,
    "blur_strength": 1.0,
    "strength": 0.6,
    "start_percent": 0.0,
    "end_percent": 1.0,
    "tile_method": "Mixture of Diffusers",
    "tile_overlap": 128,
    "tile_size": 768,
    "threshold": 0.20,
    "dilation": 5,
    "crop_factor": 2.0,
    "drop_size": 10,
    "labels": "all",
    "detailer_guide_size": 1024,
    "detailer_guide_size_for_bbox": true,
    "detailer_max_size": 1280,
    "detailer_seed": 4,
    "detailer_steps": 4,
    "detailer_cfg": 1.5,
    "detailer_sampler_name": "dpmpp_sde",
    "detailer_scheduler": "karras",
    "detailer_denoise": 0.42,
    "detailer_feather": 5,
    "detailer_noise_mask": true,
    "detailer_force_inpaint": true,
    "detailer_cycle": 1,
    "detailer_inpaint_model": false,
    "detailer_noise_mask_feather": 20,
    "color_method": "hm-mvgd-hm",
    "blend_factor": 0.5,
    "blend_mode": "normal",
    "blending_mode": "color",
    "blending_blend_percentage": 1.0,
    "vram": 48,
    "upscale_mp": 3,
    "w_tiles": 4,
    "h_tiles": 4
}